README.md
setup.py
reproduciblesignrates/__init__.py
reproduciblesignrates/hoeffding.py
reproduciblesignrates/process.py
reproduciblesignrates/sweeps.py
reproduciblesignrates.egg-info/PKG-INFO
reproduciblesignrates.egg-info/SOURCES.txt
reproduciblesignrates.egg-info/dependency_links.txt
reproduciblesignrates.egg-info/requires.txt
reproduciblesignrates.egg-info/top_level.txt