Metadata-Version: 1.0
Name: reproduciblesignrates
Version: 0.0.1
Summary: Tools for evaluating cross-replicate reproducibility
Home-page: UNKNOWN
Author: Jackson Loper, Robert Barton, Meena Subramaniam, Maxime Dhainaut, Jeffrey Regier
Author-email: UNKNOWN
License: UNKNOWN
Platform: UNKNOWN
